{
    "itm_wtr": {
        "name": "Holy Water",
        "description": {
            "summary": "Effective against the undead.",
            "detailed": "Water from the Lake of Gela stored in a glass bottle. This water is said to expel evil from undead creatures."
        },
        "use_text": "You splash some Holy Water into the face of the skeleton.",
        "uses": 0,
        "damage": 100       
    },
    "itm_r_bk": {
        "name": "Book of Riddles",  
        "description": {
            "summary": "Full of riddles and their answers.",
            "detailed": "A book filled with a range of riddles and their answers. Useful for sucking the fun out of puzzles."
            },
        "use_text": "You search the index of the book for the PLACEHOLDER's riddle and find the answer."
        },

    "itm_t_bk": {
        "name": "Book of Traps",  
        "description": {
            "summary": "Details common traps and how to spot them.",
            "detailed": "A book filled with detailed blueprints of common traps and how to spot and defuse them. Useful for avoiding nasty surprises."
            },
        "use_text": "You consult the “Spotting traps” chapter.\nAfter observing every inch of the room, you notice something suspicious."
        },

    "itm_c_bk": {
        "name": "Book of Incantations",  
        "description": {
            "summary": "Promises great power within.",
            "detailed": "A dusty tome authored by the Ancient Edoc Imanok. The book seems to have been saved from a fire long ago."
            },
        "use_text": "You flip through the scorched pages until you come upon a single readable passage: 'Once in a state of observation, focus your mind on these runes: ^^vv<><>.'"
        },

    "itm_hp": {
        "name": "Health Potion", 
        "description": {
            "summary": "Heals wounds.",
            "detailed": "A healing elixir brewed by the Ancient Alchemists. It warms your hand through the glass bottle."
            },
        "use_text": "You down the contents of the bottle. A warmth spreads through your body, healing some of your wounds.",
        "uses": 0
        },

    "itm_key": {
        "name": "Skeleton Key",  
        "description": {
            "summary": "Can open any key-operated lock.",
            "detailed": "A magical key with a skull engraved into its head that is able to open any lock. You found it in an abandoned temple."
            },
        "use_text": "You slide the key into the lock. As you turn it, you feel a biting pain on your thumb.\nStaring at the skull engraved on the Skeleton Key's head, you notice its teeth are now bloodied.\nThe chest unlocks.",
        "damage": 5
        },
    
    "itm_prl": {
        "name": "Gela Pearl",
        "description": {
            "summary": "Lightly glowing.",
            "detailed": "A pearl formed by a colossal clam at the bottom of the Lake of Gela. It retains a fragment of the lake's spirit."
        },
        "use_text": "You place the pearl in the small divot on the side of the plinth.\nA low rumbling reminiscent of the sound of crashing waves sounds in the distance, and the clamshell opens to reveal a pile of treasure.",
        "uses": 0
        },

    "itm_swrd": {
        "name": "Sword",
        "description": {
            "summary": "Is it possible to disembowel a skeleton?",
            "detailed": "A steel shortsword that, though dulled, is still sufficient to defend yourself with."
        },
        "use_text": "Your sword swings and sticks into the side of the skeleton. A raspy shriek escapes its skull as you rip the sword back out, taking a rib with it.",
        "damage": 23
        },

    "itm_map": {
        "name": "Map",
        "description": {
            "summary": "Magic paper.",
            "detailed": "A map of the dungeon. A simple enchantment upon it shows you your current location. You stole it from your now-former employer."
        },
        "use_text": "You unfurl the map."      
        },

    "itm_trch": {
        "name": "Torch",
        "description": {
            "summary": "Able to burn dry material.",
            "detailed": "A flaming torch that can be used to burn away dry material. Such as vines. Hint hint."
        },
        "use_text": "You bring the torch close to the thinner of the vines.\nThe tips of the flames lick their shrivelled leaves, setting the whole mass of tendrils aflame.\nThe room is momentarily filled with an intense warmth, but it eventually dies away, being replaced by the cold of the stone walls of the dungeon.\nThe way forward is no longer obstructed."      
        },

    "itm_btl": {
        "name": "Glass Bottle",
        "description": {
            "summary": "Completely empty.",
            "detailed": "An empty glass bottle with a cork. Could be used to hold something."
        },
        "use_text": "You uncork the bottle gently and submerge it in the water, allowing it to fill completely.\nAs you reinsert the cork, you notice the almost pearlescent quality of the water against the light of the bioluminescent bulbs above.",
        "uses": 0    
        },

    "itm_pbl": {
        "name": "Pebbles",
        "description": {
            "summary": "Harmless.",
            "detailed": "Small, round stones. They've most likely made their way into the dungeon from the Lake of Gela through the subterranean rivers that feed the resevoir."
        },
        "use_text": "You take a pebble from your collection and rub it between your fingers.\nIts cool, smooth surface calms you.",
        "uses": 0
        },

    "itm_invs": {
        "name": "Invisibility Potion",
        "description": {
            "summary": "Avoid enemy encounters with this one simple trick!",
            "detailed": "This unique ancient elixir bestows upon the drinker the power of invisibility. Useful for bad fighters."
        },
        "use_text": "."      
        }
}